Metadata-Version: 1.0
Name: gitator
Version: 0.1.36
Summary: Basic git functionality
Home-page: http://github.com/enkelbr/gitator
Author: Gustavo Maia
Author-email: gurumaia@gmail.com
License: GPL
Platform: UNKNOWN
